{
  "alerts": {
    "settings": {
      "language": {
        "validation": {
          "required": "Language is required"
        }
      },
      "theme": {
        "validation": {
          "required": "Theme is required"
        }
      },
      "save": {
        "success": {
          "title": "Settings saved successfully"
        },
        "error": {
          "title": "Failed to save settings"
        }
      }
    },
    "errors": {
      "unauthenicated": "Please login to continue"
    },
    "login": {
      "email": {
        "validation": {
          "invalid": "Please provide a valid email"
        }
      },
      "password": {
        "validation": {
          "required": "Password is required",
          "invalid": "Password must be at least 6 characters long"
        }
      },
      "error": {
        "title": "Login failed"
      }
    }
  }
}